teichicrypt/__init__.py
teichicrypt/__main__.py
teichicrypt-1.2.2.dist-info/LICENSE
teichicrypt-1.2.2.dist-info/METADATA
teichicrypt-1.2.2.dist-info/WHEEL
teichicrypt-1.2.2.dist-info/entry_points.txt
teichicrypt-1.2.2.dist-info/top_level.txt
teichicrypt-1.2.2.dist-info/RECORD
