Metadata-Version: 2.1
Name: teichicrypt
Version: 1.2.2
Summary: self build crypting algorithm
Home-page: https://github.com/tobi08151405/crypt
Author: Teichi
Author-email: tobias@teichmann.top
License: UNKNOWN
Platform: UNKNOWN
Classifier: Programming Language :: Python :: 3
Classifier: License :: OSI Approved :: GNU General Public License v3 (GPLv3)
Classifier: Operating System :: OS Independent
Requires-Dist: mpmath
